pyInfinityFlow/Debugging_Utilities.py
pyInfinityFlow/InfinityFlow_Utilities.py
pyInfinityFlow/Plotting_Utilities.py
pyInfinityFlow/Transformations.py
pyInfinityFlow/__init__.py
pyInfinityFlow/fcs_io.py
pyInfinityFlow/pyInfinityFlow.py
pyInfinityFlow/pyInfinityFlow_list_channels.py
pyInfinityFlow/pyInfinityFlow_with_args.py
pyInfinityFlow-1.0.0.dist-info/LICENSE
pyInfinityFlow-1.0.0.dist-info/METADATA
pyInfinityFlow-1.0.0.dist-info/WHEEL
pyInfinityFlow-1.0.0.dist-info/entry_points.txt
pyInfinityFlow-1.0.0.dist-info/top_level.txt
pyInfinityFlow-1.0.0.dist-info/RECORD
