Metadata-Version: 2.1
Name: pyInfinityFlow
Version: 1.0.0
Summary: Impute Flow Cytometry values between overlapping panels with XGBoost regression.
Home-page: https://github.com/KyleFerchen/pyInfinityFlow
Author: Kyle Ferchen
Author-email: Kyle Ferchen <ferchenkyle@gmail.com>
License: MIT License
Project-URL: Homepage, https://github.com/KyleFerchen/pyInfinityFlow
Project-URL: Bug Tracker, https://github.com/KyleFerchen/pyInfinityFlow/issues
Classifier: Programming Language :: Python :: 3
Classifier: License :: OSI Approved :: MIT License
Classifier: Operating System :: OS Independent
Requires-Python: >=3.8
License-File: LICENSE
Requires-Dist: umap-learn >=0.5
Requires-Dist: xgboost >=1.6
Requires-Dist: scanpy >=1.9
Requires-Dist: pyarrow >=9.0
Requires-Dist: leidenalg
Provides-Extra: doc
Requires-Dist: sphinx ~=4.5.0 ; extra == 'doc'
Requires-Dist: myst-parser ; extra == 'doc'
Requires-Dist: nbsphinx ; extra == 'doc'
